[
  {
    "full_name": "EPMatt/awesome-ha-blueprints",
    "stargazers_count": 767,
    "open_issues_count": 190,
    "forks_count": 219
  },
  {
    "full_name": "Ezard/semantic-prs",
    "stargazers_count": 99,
    "open_issues_count": 8,
    "forks_count": 10
  },
  {
    "full_name": "corporategoth/ha-powerpetdoor",
    "stargazers_count": 12,
    "open_issues_count": 2,
    "forks_count": 4
  },
  {
    "full_name": "ChuckPa/PlexDBRepair",
    "stargazers_count": 522,
    "open_issues_count": 0,
    "forks_count": 32
  },
  {
    "full_name": "badaix/snapcast",
    "stargazers_count": 5626,
    "open_issues_count": 92,
    "forks_count": 433
  },
  {
    "full_name": "DonMcD/ultimate-plex-stack",
    "stargazers_count": 91,
    "open_issues_count": 4,
    "forks_count": 7
  },
  {
    "full_name": "renovatebot/github-action",
    "stargazers_count": 221,
    "open_issues_count": 13,
    "forks_count": 67
  },
  {
    "full_name": "IDmedia/hass-unraid",
    "stargazers_count": 21,
    "open_issues_count": 0,
    "forks_count": 0
  },
  {
    "full_name": "Clooos/Bubble-Card",
    "stargazers_count": 1097,
    "open_issues_count": 42,
    "forks_count": 28
  },
  {
    "full_name": "jorenn92/Maintainerr",
    "stargazers_count": 375,
    "open_issues_count": 12,
    "forks_count": 8
  },
  {
    "full_name": "ThomasLomas/ha-starlinghomehub",
    "stargazers_count": 3,
    "open_issues_count": 1,
    "forks_count": 0
  },
  {
    "full_name": "mlamberts78/weather-chart-card",
    "stargazers_count": 141,
    "open_issues_count": 4,
    "forks_count": 10
  },
  {
    "full_name": "ikatyang/linguist-languages",
    "stargazers_count": 19,
    "open_issues_count": 1,
    "forks_count": 3
  },
  {
    "full_name": "bmcclure/ha-chore-helper",
    "stargazers_count": 27,
    "open_issues_count": 10,
    "forks_count": 4
  },
  {
    "full_name": "allangood/rtlamr2mqtt",
    "stargazers_count": 245,
    "open_issues_count": 14,
    "forks_count": 44
  },
  {
    "full_name": "Deejayfool/hass-shutter-card",
    "stargazers_count": 236,
    "open_issues_count": 66,
    "forks_count": 91
  },
  {
    "full_name": "j-a-n/lovelace-wallpanel",
    "stargazers_count": 347,
    "open_issues_count": 18,
    "forks_count": 32
  },
  {
    "full_name": "dermotduffy/frigate-hass-card",
    "stargazers_count": 422,
    "open_issues_count": 64,
    "forks_count": 44
  },
  {
    "full_name": "bokub/rgb-light-card",
    "stargazers_count": 394,
    "open_issues_count": 7,
    "forks_count": 24
  },
  {
    "full_name": "twrecked/hass-virtual",
    "stargazers_count": 130,
    "open_issues_count": 39,
    "forks_count": 23
  },
  {
    "full_name": "retronas/retronas",
    "stargazers_count": 609,
    "open_issues_count": 1,
    "forks_count": 37
  },
  {
    "full_name": "getsentry/action-github-app-token",
    "stargazers_count": 173,
    "open_issues_count": 19,
    "forks_count": 91
  },
  {
    "full_name": "RimacTechnology/semantic-release-monorepo",
    "stargazers_count": 6,
    "open_issues_count": 0,
    "forks_count": 1
  },
  {
    "full_name": "devops-kung-fu/bomber",
    "stargazers_count": 423,
    "open_issues_count": 14,
    "forks_count": 36
  },
  {
    "full_name": "snyk/parlay",
    "stargazers_count": 87,
    "open_issues_count": 14,
    "forks_count": 15
  },
  {
    "full_name": "matt8707/ha-fusion",
    "stargazers_count": 1400,
    "open_issues_count": 66,
    "forks_count": 56
  },
  {
    "full_name": "boneskull/midnight-smoker",
    "stargazers_count": 25,
    "open_issues_count": 38,
    "forks_count": 1
  },
  {
    "full_name": "ga2mer/ha-zepp",
    "stargazers_count": 51,
    "open_issues_count": 4,
    "forks_count": 13
  },
  {
    "full_name": "daggerok/gitignore-idea-runConfigurations",
    "stargazers_count": 5,
    "open_issues_count": 0,
    "forks_count": 0
  },
  {
    "full_name": "Makin-Things/weather-radar-card",
    "stargazers_count": 177,
    "open_issues_count": 26,
    "forks_count": 11
  }
]