[
  {
    "full_name": "Aleks130699/ha-fpp",
    "stargazers_count": 12,
    "open_issues_count": 2,
    "forks_count": 2
  },
  {
    "full_name": "koolsb/ha-fpp",
    "stargazers_count": 7,
    "open_issues_count": 6,
    "forks_count": 6
  },
  {
    "full_name": "jrt45840/Chore_HA",
    "stargazers_count": 16,
    "open_issues_count": 0,
    "forks_count": 0
  },
  {
    "full_name": "Morcatko/EspHome-Editor",
    "stargazers_count": 15,
    "open_issues_count": 6,
    "forks_count": 0
  },
  {
    "full_name": "koromar/FanBuddy",
    "stargazers_count": 6,
    "open_issues_count": 0,
    "forks_count": 0
  },
  {
    "full_name": "Hankanman/Area-Occupancy-Detection",
    "stargazers_count": 3,
    "open_issues_count": 0,
    "forks_count": 0
  },
  {
    "full_name": "google/gts",
    "stargazers_count": 5101,
    "open_issues_count": 47,
    "forks_count": 209
  },
  {
    "full_name": "ChazLayyd/Bambu-Lab-Klipper-Conversion",
    "stargazers_count": 37,
    "open_issues_count": 0,
    "forks_count": 1
  },
  {
    "full_name": "ShonP40/Car-Assistant",
    "stargazers_count": 20,
    "open_issues_count": 1,
    "forks_count": 2
  },
  {
    "full_name": "TazzerMAN/increase_swap_addon",
    "stargazers_count": 33,
    "open_issues_count": 1,
    "forks_count": 2
  },
  {
    "full_name": "jneilliii/OctoPrint-BambuPrinter",
    "stargazers_count": 146,
    "open_issues_count": 25,
    "forks_count": 9
  },
  {
    "full_name": "geappliances/home-assistant-adapter",
    "stargazers_count": 10,
    "open_issues_count": 3,
    "forks_count": 2
  },
  {
    "full_name": "geappliances/home-assistant-bridge",
    "stargazers_count": 12,
    "open_issues_count": 0,
    "forks_count": 0
  },
  {
    "full_name": "giltayar/jsdoc-typing",
    "stargazers_count": 36,
    "open_issues_count": 1,
    "forks_count": 2
  },
  {
    "full_name": "basbruss/adaptive-cover",
    "stargazers_count": 132,
    "open_issues_count": 39,
    "forks_count": 13
  },
  {
    "full_name": "github/entitlements-app",
    "stargazers_count": 429,
    "open_issues_count": 2,
    "forks_count": 18
  },
  {
    "full_name": "dylandoamaral/uptime-card",
    "stargazers_count": 278,
    "open_issues_count": 4,
    "forks_count": 11
  },
  {
    "full_name": "gcormier/esphome-pressure",
    "stargazers_count": 51,
    "open_issues_count": 2,
    "forks_count": 1
  },
  {
    "full_name": "PRProd/HA-Firemote",
    "stargazers_count": 551,
    "open_issues_count": 18,
    "forks_count": 72
  },
  {
    "full_name": "domalab/ha-unraid",
    "stargazers_count": 43,
    "open_issues_count": 15,
    "forks_count": 2
  },
  {
    "full_name": "Stengo/DeskPad",
    "stargazers_count": 5472,
    "open_issues_count": 21,
    "forks_count": 94
  },
  {
    "full_name": "travissmithv1/dora-metrics-example",
    "stargazers_count": 2,
    "open_issues_count": 0,
    "forks_count": 0
  },
  {
    "full_name": "ataylorme/eslint-annotate-action",
    "stargazers_count": 99,
    "open_issues_count": 6,
    "forks_count": 33
  },
  {
    "full_name": "bridgecrewio/yor",
    "stargazers_count": 834,
    "open_issues_count": 7,
    "forks_count": 125
  },
  {
    "full_name": "recyclarr/recyclarr",
    "stargazers_count": 1172,
    "open_issues_count": 21,
    "forks_count": 31
  },
  {
    "full_name": "Commifreak/unraid-appdata.backup",
    "stargazers_count": 24,
    "open_issues_count": 14,
    "forks_count": 1
  },
  {
    "full_name": "greghesp/ha-bambulab",
    "stargazers_count": 1061,
    "open_issues_count": 25,
    "forks_count": 95
  },
  {
    "full_name": "ngocjohn/lunar-phase-card",
    "stargazers_count": 76,
    "open_issues_count": 0,
    "forks_count": 12
  },
  {
    "full_name": "ngocjohn/vehicle-status-card",
    "stargazers_count": 47,
    "open_issues_count": 1,
    "forks_count": 3
  },
  {
    "full_name": "sirkirby/ha-udm-rule-manager",
    "stargazers_count": 9,
    "open_issues_count": 1,
    "forks_count": 1
  }
]